edgebenchmark/__init__.py
edgebenchmark/custom_types.py
edgebenchmark/edgebenchmark.py
edgebenchmark/edgebenchmark_cli.py
edgebenchmark/ncnn_benchmark.py
edgebenchmark/ncnn_benchmark_20210124.py
edgebenchmark/settings.py
edgebenchmark/tflite_benchmark.py
edgebenchmark/tflite_benchmark_1_14_0.py
edgebenchmark/tflite_benchmark_1_15_0.py
edgebenchmark/tflite_benchmark_2_0_0.py
edgebenchmark/tflite_benchmark_2_1_0.py
edgebenchmark/tflite_benchmark_2_2_0.py
edgebenchmark/tflite_benchmark_2_3_0.py
edgebenchmark/tflite_benchmark_2_4_0.py
edgebenchmark/utils.py
edgebenchmark-0.0.11.dist-info/LICENSE
edgebenchmark-0.0.11.dist-info/METADATA
edgebenchmark-0.0.11.dist-info/WHEEL
edgebenchmark-0.0.11.dist-info/entry_points.txt
edgebenchmark-0.0.11.dist-info/top_level.txt
edgebenchmark-0.0.11.dist-info/RECORD
