Metadata-Version: 2.1
Name: edgebenchmark
Version: 0.0.11
Summary: Tool to benchmark speed of machine learning models on real mobile devices
Home-page: https://github.com/bisonai/edgebenchmark
Author: Bisonai
Author-email: contact@bisonai.com
License: UNKNOWN
Platform: UNKNOWN
Classifier: Programming Language :: Python :: 3
Classifier: License :: OSI Approved :: Apache Software License
Classifier: Operating System :: OS Independent
Requires-Python: >=3.6
Requires-Dist: click (>=7.1.2)
Requires-Dist: requests (>=2.24.0)
